drives/__init__.py
drives-0.0.1.dist-info/LICENSE
drives-0.0.1.dist-info/WHEEL
drives-0.0.1.dist-info/METADATA
drives-0.0.1.dist-info/RECORD
