Metadata-Version: 2.1
Name: drives
Version: 0.0.1
Summary: Drives for Humans™
Home-page: https://pypi.org/project/drives
License: BSD-3-Clause
Author: Yi Zhang
Author-email: yizhang.dev@gmail.com
Requires-Python: >=3.7,<4.0
Classifier: License :: OSI Approved :: BSD License
Classifier: Programming Language :: Python :: 3
Classifier: Programming Language :: Python :: 3.7
Classifier: Programming Language :: Python :: 3.8
Classifier: Programming Language :: Python :: 3.9
Classifier: Programming Language :: Python :: 3.10
Classifier: Programming Language :: Python :: 3.11
Project-URL: Documentation, https://drives.readthedocs.io/en/latest/
Project-URL: Repository, https://github.com/imyizhang/drives
